src/design/fail_counter.sv
module fail_counter #(parameter MAX_FALLOS = 99) (
  input logic clk,
  input logic rst, //rst_failure
  input logic miss,
  input logic hit,
  input logic nueva_partida,
  input logic cont_failure,

  output logic [7:0] fallo,
  output logic fin_partida
  );

  // La idea es hacer dos contadores independientes como dice el .md para este diseño en las secciones g) & h)
  // 1. Acumulado en BCD, es la misma idea a lo que ya hice en hit_counter, entonces nada más le voy a cambiar lo que no quiero con miss
  // 2. fin_partida, esto es solo la tabla del punto h) pero implementada

  // 1. De aquí hasta 'FIN' es exáctamente lo mismo que en hit_counter pero con fallo en vez de acierto
  localparam MAX_UNIDADES = MAX_FALLOS / 33; // dígito de unidades del techo, Ej: 99/33 =3
  localparam MAX_DECENAS  = 0; // dígito de decenas del techo, Ej: 99/10 = 9

  logic [3:0] unidades, decenas;

  always_ff @(posedge clk) begin
    if (rst || nueva_partida || hit) begin // reset gana aunque llegue hit el mismo ciclo
      unidades <= 0;
      decenas  <= 0;
    end
    // Acarreo
    else if (miss && unidades == MAX_UNIDADES && decenas != MAX_DECENAS) begin // acierto y unidades llegó al tope, pero decenas todavía no hay acarreo
      unidades <= 0; // acarreo, las unidades a 0, las decenas suben
      decenas  <= decenas + 1;
    end
    // Incremento normal 
    else if (miss && unidades != MAX_UNIDADES) begin // acierto y unidades todavía no llega al límite
      unidades <= unidades + 1;
    end
  end

  assign fallo[3:0] = unidades;
  assign fallo[7:4] = decenas;
  // FIN


  // 2.
  logic [1:0] consecutivos; // <-- Sirve para fallos consecutivos, es interno. 2 bits porque llega hasta el valor '3'

  always_ff @(posedge clk) begin
    if(rst || nueva_partida || hit ) begin // Se lee como: "Si hay reset O nueva partida O un hit"
      consecutivos <= 0; // significa que se acabó la racha de fallos o todavía no existe
    end
    else if(miss) begin
      if(consecutivos == 2 || consecutivos == 3) // Se lee como: "¿La racha ya estaba a un fallo de terminar, o ya había terminado?"
        consecutivos <= 3; // Deja la racha fija como el máximo 3
      else
        consecutivos <= consecutivos + 1; // racha todavía corta (0 o 1), sube uno más
    end
  end

  // fin_partida se calcula de forma combinacional (no registrada) para
  // que esté lista en el MISMO ciclo del fallo que la dispara. Antes
  // estaba registrada, así que su valor nuevo solo se veía un ciclo
  // después del fallo que la disparaba -- justo el mismo ciclo en que
  // la fsm ya necesita leer cont_failure dentro del estado FAILURE, lo
  // que hacía que el 3er fallo consecutivo pasara desapercibido y
  // hiciera falta un 4to fallo para llegar a GAME_OVER.
  assign fin_partida = miss && (consecutivos == 2 || consecutivos == 3);

endmodule

src/sim/tb_fail_counter.sv
`timescale 1ns/1ps

module tb_fail_counter;

  localparam MAX_FALLOS_TB = 99; // <-- techo real de la tarjeta

  logic clk_tb;
  logic rst_tb;
  logic nueva_partida_tb;
  logic miss_tb;
  logic hit_tb;

  logic [7:0] fallo_tb;
  logic fin_partida_tb;
  int misses_T; // cuenta cuantos miss_pulso se han mandado, para los $display (misses TOTALES)

  fail_counter #(
    .MAX_FALLOS(MAX_FALLOS_TB)
  ) dut_fail_counter (
    .clk(clk_tb),
    .rst(rst_tb),
    .miss(miss_tb),
    .hit(hit_tb),
    .nueva_partida(nueva_partida_tb),
    .fallo(fallo_tb),
    .fin_partida(fin_partida_tb)
  );

  always #5 clk_tb = ~clk_tb;

  task automatic miss_pulso; // El pulso es un miss cada ciclo
    begin
      miss_tb = 1;
      #10;
      miss_tb = 0;
      #10;
      misses_T = misses_T + 1;
    end
  endtask

  task automatic hit_pulso; // El pulso es un hit cada ciclo, sirve para romper la racha de consecutivos
    begin
      hit_tb = 1;
      #10;
      hit_tb = 0;
      #10;
    end
  endtask

  initial begin
    $dumpfile("tb_fail_counter.vcd");
    $dumpvars(0, tb_fail_counter);

    // Todas en reposo, rst arranca en 1 para forzar el reset inicial
    clk_tb = 0;
    rst_tb = 1;
    nueva_partida_tb = 0;
    miss_tb = 0;
    hit_tb = 0;
    misses_T = 0;

    #20;
    rst_tb = 0;

    #10; // <-- tiempo despues soltar el rst
    $display("\n\nRESET: fallo=%0d consecutivos=%0d fin_partida=%b t=%0t", fallo_tb, dut_fail_counter.consecutivos, fin_partida_tb, $time);

    // Parte 1, acumulado BCD igual que tb_hit_counter pero con miss, fin_partida queda en 1 desde el tercer miss porque nada la limpia aca
    repeat (9) miss_pulso(); // incremento normal hasta justo antes del acarreo
    $display("\nParte 1");
    $display("%0d misses: fallo=%0d (decenas=%0d unidades=%0d) consecutivos=%0d fin_partida=%b t=%0t", misses_T, fallo_tb, dut_fail_counter.decenas, dut_fail_counter.unidades, dut_fail_counter.consecutivos, fin_partida_tb, $time);

    miss_pulso(); // este miss hace el acarreo, unidades vuelve a 0 y decenas sube
    $display("%0d misses (primer & único acarreo): fallo=%0d (decenas=%0d unidades=%0d) consecutivos=%0d fin_partida=%b t=%0t", misses_T, fallo_tb, dut_fail_counter.decenas, dut_fail_counter.unidades, dut_fail_counter.consecutivos, fin_partida_tb, $time);

    repeat (MAX_FALLOS_TB - misses_T - 1) miss_pulso(); // sigue subiendo normal hasta casi llegar a MAX_FALLOS_TB
    $display("%0d misses: fallo=%0d (decenas=%0d unidades=%0d) consecutivos=%0d fin_partida=%b t=%0t", misses_T, fallo_tb, dut_fail_counter.decenas, dut_fail_counter.unidades, dut_fail_counter.consecutivos, fin_partida_tb, $time);

    miss_pulso(); // este miss llega exacto al techo
    $display("%0d misses (máx): fallo=%0d (decenas=%0d unidades=%0d) consecutivos=%0d fin_partida=%b t=%0t", misses_T, fallo_tb, dut_fail_counter.decenas, dut_fail_counter.unidades, dut_fail_counter.consecutivos, fin_partida_tb, $time);

    miss_pulso(); // un miss de más, ya en el máx, no debe subir
    $display("%0d misses (máx): fallo=%0d (decenas=%0d unidades=%0d) consecutivos=%0d fin_partida=%b t=%0t", misses_T, fallo_tb, dut_fail_counter.decenas, dut_fail_counter.unidades, dut_fail_counter.consecutivos, fin_partida_tb, $time);

    // Parte 2, racha de consecutivos y fin_partida
    #10;
    nueva_partida_tb = 1; // limpia fallo, consecutivos y fin_partida, arranca partida nueva
    #10;
    nueva_partida_tb = 0;
    #10;
    $display("\nParte 2: Racha de consecutivos & fin_partida");
    $display("NUEVA_PARTIDA: fallo=%0d consecutivos=%0d fin_partida=%b t=%0t", fallo_tb, dut_fail_counter.consecutivos, fin_partida_tb, $time);

    repeat (2) miss_pulso(); // dos fallos seguidos, racha a punto de terminar la partida
    $display("2 misses seguidos: fallo=%0d consecutivos=%0d fin_partida=%b t=%0t", fallo_tb, dut_fail_counter.consecutivos, fin_partida_tb, $time);

    hit_pulso(); // el hit rompe la racha, pero NO debe tocar el acumulado fallo
    $display("HIT rompe la racha: fallo=%0d consecutivos=%0d fin_partida=%b t=%0t", fallo_tb, dut_fail_counter.consecutivos, fin_partida_tb, $time);

    repeat (3) miss_pulso(); // tres fallos seguidos, ahora sí se cumple la condición de fin de partida
    $display("3 misses seguidos: fallo=%0d consecutivos=%0d fin_partida=%b t=%0t", fallo_tb, dut_fail_counter.consecutivos, fin_partida_tb, $time);

    miss_pulso(); // un cuarto miss seguido, consecutivos y fin_partida ya en el máx 3/1
    $display("4to miss seguido (máx): fallo=%0d consecutivos=%0d fin_partida=%b t=%0t", fallo_tb, dut_fail_counter.consecutivos, fin_partida_tb, $time);

    hit_pulso(); // el hit limpia la racha y fin_partida aunque la partida ya "había terminado" para este módulo
    $display("HIT tras fin_partida: fallo=%0d consecutivos=%0d fin_partida=%b t=%0t", fallo_tb, dut_fail_counter.consecutivos, fin_partida_tb, $time);

    // Parte 3, reset simultáneo con miss
    #10;
    nueva_partida_tb = 1;
    miss_tb = 1;
    #10;
    nueva_partida_tb = 0;
    miss_tb = 0;
    #10;
    $display("\nParte 3: Reset simultáneo con miss");
    $display("NUEVA_PARTIDA + MISS simultáneo: fallo=%0d consecutivos=%0d fin_partida=%b t=%0t", fallo_tb, dut_fail_counter.consecutivos, fin_partida_tb, $time);

    #10;
    rst_tb = 1;
    miss_tb = 1;
    #10;
    rst_tb = 0;
    miss_tb = 0;
    #10;
    $display("RST + MISS simultáneo: fallo=%0d consecutivos=%0d fin_partida=%b t=%0t", fallo_tb, dut_fail_counter.consecutivos, fin_partida_tb, $time);

    #20; // <-- margen final antes de terminar
    $finish;
  end

endmodule

// Parte 1, acarreo justo en el miss 10, techo exacto en el miss 99, en el máx desde el miss 100, consecutivos/fin_partida en 3/1 desde el miss 3
// Parte 2, un hit limpia consecutivos y fin_partida sin bajar fallo, y 3 miss seguidos sí activan fin_partida
// Parte 3, nueva_partida+miss y rst+miss simultáneos terminan en todo cero, el reset gana sobre el miss

src/build/tb_fail_counter.vcd
$date
	Wed Aug 26 15:24:07 2026
$end
$version
	Icarus Verilog
$end
$timescale
	1ps
$end
$scope module tb_fail_counter $end
$var wire 1 ! fin_partida_tb $end
$var wire 8 " fallo_tb [7:0] $end
$var parameter 32 # MAX_FALLOS_TB $end
$var reg 1 $ clk_tb $end
$var reg 1 % hit_tb $end
$var reg 1 & miss_tb $end
$var reg 1 ' nueva_partida_tb $end
$var reg 1 ( rst_tb $end
$var integer 32 ) misses_T [31:0] $end
$scope module dut_fail_counter $end
$var wire 1 $ clk $end
$var wire 1 ! fin_partida $end
$var wire 1 % hit $end
$var wire 1 & miss $end
$var wire 1 ' nueva_partida $end
$var wire 1 ( rst $end
$var wire 8 * fallo [7:0] $end
$var parameter 32 + MAX_DECENAS $end
$var parameter 32 , MAX_FALLOS $end
$var parameter 32 - MAX_UNIDADES $end
$var reg 2 . consecutivos [1:0] $end
$var reg 4 / decenas [3:0] $end
$var reg 4 0 unidades [3:0] $end
$upscope $end
$scope task hit_pulso $end
$upscope $end
$scope task miss_pulso $end
$upscope $end
$upscope $end
$enddefinitions $end
$comment Show the parameter values. $end
$dumpall
b1001 -
b1100011 ,
b1001 +
b1100011 #
$end
#0
$dumpvars
bx 0
bx /
bx .
bx *
b0 )
1(
0'
0&
0%
0$
bx "
0!
$end
#5000
b0 /
b0 "
b0 *
b0 0
b0 .
1$
#10000
0$
#15000
1$
#20000
0$
0(
#25000
1$
#30000
0$
1&
#35000
b1 .
b1 "
b1 *
b1 0
1$
#40000
0$
0&
#45000
1$
#50000
0$
1&
b1 )
#55000
1!
b10 .
b10 "
b10 *
b10 0
1$
#60000
0!
0$
0&
#65000
1$
#70000
1!
0$
1&
b10 )
#75000
b11 .
b11 "
b11 *
b11 0
1$
#80000
0!
0$
0&
#85000
1$
#90000
1!
0$
1&
b11 )
#95000
b100 "
b100 *
b100 0
1$
#100000
0!
0$
0&
#105000
1$
#110000
1!
0$
1&
b100 )
#115000
b101 "
b101 *
b101 0
1$
#120000
0!
0$
0&
#125000
1$
#130000
1!
0$
1&
b101 )
#135000
b110 "
b110 *
b110 0
1$
#140000
0!
0$
0&
#145000
1$
#150000
1!
0$
1&
b110 )
#155000
b111 "
b111 *
b111 0
1$
#160000
0!
0$
0&
#165000
1$
#170000
1!
0$
1&
b111 )
#175000
b1000 "
b1000 *
b1000 0
1$
#180000
0!
0$
0&
#185000
1$
#190000
1!
0$
1&
b1000 )
#195000
b1001 "
b1001 *
b1001 0
1$
#200000
0!
0$
0&
#205000
1$
#210000
1!
0$
1&
b1001 )
#215000
b1 /
b10000 "
b10000 *
b0 0
1$
#220000
0!
0$
0&
#225000
1$
#230000
1!
0$
1&
b1010 )
#235000
b10001 "
b10001 *
b1 0
1$
#240000
0!
0$
0&
#245000
1$
#250000
1!
0$
1&
b1011 )
#255000
b10010 "
b10010 *
b10 0
1$
#260000
0!
0$
0&
#265000
1$
#270000
1!
0$
1&
b1100 )
#275000
b10011 "
b10011 *
b11 0
1$
#280000
0!
0$
0&
#285000
1$
#290000
1!
0$
1&
b1101 )
#295000
b10100 "
b10100 *
b100 0
1$
#300000
0!
0$
0&
#305000
1$
#310000
1!
0$
1&
b1110 )
#315000
b10101 "
b10101 *
b101 0
1$
#320000
0!
0$
0&
#325000
1$
#330000
1!
0$
1&
b1111 )
#335000
b10110 "
b10110 *
b110 0
1$
#340000
0!
0$
0&
#345000
1$
#350000
1!
0$
1&
b10000 )
#355000
b10111 "
b10111 *
b111 0
1$
#360000
0!
0$
0&
#365000
1$
#370000
1!
0$
1&
b10001 )
#375000
b11000 "
b11000 *
b1000 0
1$
#380000
0!
0$
0&
#385000
1$
#390000
1!
0$
1&
b10010 )
#395000
b11001 "
b11001 *
b1001 0
1$
#400000
0!
0$
0&
#405000
1$
#410000
1!
0$
1&
b10011 )
#415000
b10 /
b100000 "
b100000 *
b0 0
1$
#420000
0!
0$
0&
#425000
1$
#430000
1!
0$
1&
b10100 )
#435000
b100001 "
b100001 *
b1 0
1$
#440000
0!
0$
0&
#445000
1$
#450000
1!
0$
1&
b10101 )
#455000
b100010 "
b100010 *
b10 0
1$
#460000
0!
0$
0&
#465000
1$
#470000
1!
0$
1&
b10110 )
#475000
b100011 "
b100011 *
b11 0
1$
#480000
0!
0$
0&
#485000
1$
#490000
1!
0$
1&
b10111 )
#495000
b100100 "
b100100 *
b100 0
1$
#500000
0!
0$
0&
#505000
1$
#510000
1!
0$
1&
b11000 )
#515000
b100101 "
b100101 *
b101 0
1$
#520000
0!
0$
0&
#525000
1$
#530000
1!
0$
1&
b11001 )
#535000
b100110 "
b100110 *
b110 0
1$
#540000
0!
0$
0&
#545000
1$
#550000
1!
0$
1&
b11010 )
#555000
b100111 "
b100111 *
b111 0
1$
#560000
0!
0$
0&
#565000
1$
#570000
1!
0$
1&
b11011 )
#575000
b101000 "
b101000 *
b1000 0
1$
#580000
0!
0$
0&
#585000
1$
#590000
1!
0$
1&
b11100 )
#595000
b101001 "
b101001 *
b1001 0
1$
#600000
0!
0$
0&
#605000
1$
#610000
1!
0$
1&
b11101 )
#615000
b11 /
b110000 "
b110000 *
b0 0
1$
#620000
0!
0$
0&
#625000
1$
#630000
1!
0$
1&
b11110 )
#635000
b110001 "
b110001 *
b1 0
1$
#640000
0!
0$
0&
#645000
1$
#650000
1!
0$
1&
b11111 )
#655000
b110010 "
b110010 *
b10 0
1$
#660000
0!
0$
0&
#665000
1$
#670000
1!
0$
1&
b100000 )
#675000
b110011 "
b110011 *
b11 0
1$
#680000
0!
0$
0&
#685000
1$
#690000
1!
0$
1&
b100001 )
#695000
b110100 "
b110100 *
b100 0
1$
#700000
0!
0$
0&
#705000
1$
#710000
1!
0$
1&
b100010 )
#715000
b110101 "
b110101 *
b101 0
1$
#720000
0!
0$
0&
#725000
1$
#730000
1!
0$
1&
b100011 )
#735000
b110110 "
b110110 *
b110 0
1$
#740000
0!
0$
0&
#745000
1$
#750000
1!
0$
1&
b100100 )
#755000
b110111 "
b110111 *
b111 0
1$
#760000
0!
0$
0&
#765000
1$
#770000
1!
0$
1&
b100101 )
#775000
b111000 "
b111000 *
b1000 0
1$
#780000
0!
0$
0&
#785000
1$
#790000
1!
0$
1&
b100110 )
#795000
b111001 "
b111001 *
b1001 0
1$
#800000
0!
0$
0&
#805000
1$
#810000
1!
0$
1&
b100111 )
#815000
b100 /
b1000000 "
b1000000 *
b0 0
1$
#820000
0!
0$
0&
#825000
1$
#830000
1!
0$
1&
b101000 )
#835000
b1000001 "
b1000001 *
b1 0
1$
#840000
0!
0$
0&
#845000
1$
#850000
1!
0$
1&
b101001 )
#855000
b1000010 "
b1000010 *
b10 0
1$
#860000
0!
0$
0&
#865000
1$
#870000
1!
0$
1&
b101010 )
#875000
b1000011 "
b1000011 *
b11 0
1$
#880000
0!
0$
0&
#885000
1$
#890000
1!
0$
1&
b101011 )
#895000
b1000100 "
b1000100 *
b100 0
1$
#900000
0!
0$
0&
#905000
1$
#910000
1!
0$
1&
b101100 )
#915000
b1000101 "
b1000101 *
b101 0
1$
#920000
0!
0$
0&
#925000
1$
#930000
1!
0$
1&
b101101 )
#935000
b1000110 "
b1000110 *
b110 0
1$
#940000
0!
0$
0&
#945000
1$
#950000
1!
0$
1&
b101110 )
#955000
b1000111 "
b1000111 *
b111 0
1$
#960000
0!
0$
0&
#965000
1$
#970000
1!
0$
1&
b101111 )
#975000
b1001000 "
b1001000 *
b1000 0
1$
#980000
0!
0$
0&
#985000
1$
#990000
1!
0$
1&
b110000 )
#995000
b1001001 "
b1001001 *
b1001 0
1$
#1000000
0!
0$
0&
#1005000
1$
#1010000
1!
0$
1&
b110001 )
#1015000
b101 /
b1010000 "
b1010000 *
b0 0
1$
#1020000
0!
0$
0&
#1025000
1$
#1030000
1!
0$
1&
b110010 )
#1035000
b1010001 "
b1010001 *
b1 0
1$
#1040000
0!
0$
0&
#1045000
1$
#1050000
1!
0$
1&
b110011 )
#1055000
b1010010 "
b1010010 *
b10 0
1$
#1060000
0!
0$
0&
#1065000
1$
#1070000
1!
0$
1&
b110100 )
#1075000
b1010011 "
b1010011 *
b11 0
1$
#1080000
0!
0$
0&
#1085000
1$
#1090000
1!
0$
1&
b110101 )
#1095000
b1010100 "
b1010100 *
b100 0
1$
#1100000
0!
0$
0&
#1105000
1$
#1110000
1!
0$
1&
b110110 )
#1115000
b1010101 "
b1010101 *
b101 0
1$
#1120000
0!
0$
0&
#1125000
1$
#1130000
1!
0$
1&
b110111 )
#1135000
b1010110 "
b1010110 *
b110 0
1$
#1140000
0!
0$
0&
#1145000
1$
#1150000
1!
0$
1&
b111000 )
#1155000
b1010111 "
b1010111 *
b111 0
1$
#1160000
0!
0$
0&
#1165000
1$
#1170000
1!
0$
1&
b111001 )
#1175000
b1011000 "
b1011000 *
b1000 0
1$
#1180000
0!
0$
0&
#1185000
1$
#1190000
1!
0$
1&
b111010 )
#1195000
b1011001 "
b1011001 *
b1001 0
1$
#1200000
0!
0$
0&
#1205000
1$
#1210000
1!
0$
1&
b111011 )
#1215000
b110 /
b1100000 "
b1100000 *
b0 0
1$
#1220000
0!
0$
0&
#1225000
1$
#1230000
1!
0$
1&
b111100 )
#1235000
b1100001 "
b1100001 *
b1 0
1$
#1240000
0!
0$
0&
#1245000
1$
#1250000
1!
0$
1&
b111101 )
#1255000
b1100010 "
b1100010 *
b10 0
1$
#1260000
0!
0$
0&
#1265000
1$
#1270000
1!
0$
1&
b111110 )
#1275000
b1100011 "
b1100011 *
b11 0
1$
#1280000
0!
0$
0&
#1285000
1$
#1290000
1!
0$
1&
b111111 )
#1295000
b1100100 "
b1100100 *
b100 0
1$
#1300000
0!
0$
0&
#1305000
1$
#1310000
1!
0$
1&
b1000000 )
#1315000
b1100101 "
b1100101 *
b101 0
1$
#1320000
0!
0$
0&
#1325000
1$
#1330000
1!
0$
1&
b1000001 )
#1335000
b1100110 "
b1100110 *
b110 0
1$
#1340000
0!
0$
0&
#1345000
1$
#1350000
1!
0$
1&
b1000010 )
#1355000
b1100111 "
b1100111 *
b111 0
1$
#1360000
0!
0$
0&
#1365000
1$
#1370000
1!
0$
1&
b1000011 )
#1375000
b1101000 "
b1101000 *
b1000 0
1$
#1380000
0!
0$
0&
#1385000
1$
#1390000
1!
0$
1&
b1000100 )
#1395000
b1101001 "
b1101001 *
b1001 0
1$
#1400000
0!
0$
0&
#1405000
1$
#1410000
1!
0$
1&
b1000101 )
#1415000
b111 /
b1110000 "
b1110000 *
b0 0
1$
#1420000
0!
0$
0&
#1425000
1$
#1430000
1!
0$
1&
b1000110 )
#1435000
b1110001 "
b1110001 *
b1 0
1$
#1440000
0!
0$
0&
#1445000
1$
#1450000
1!
0$
1&
b1000111 )
#1455000
b1110010 "
b1110010 *
b10 0
1$
#1460000
0!
0$
0&
#1465000
1$
#1470000
1!
0$
1&
b1001000 )
#1475000
b1110011 "
b1110011 *
b11 0
1$
#1480000
0!
0$
0&
#1485000
1$
#1490000
1!
0$
1&
b1001001 )
#1495000
b1110100 "
b1110100 *
b100 0
1$
#1500000
0!
0$
0&
#1505000
1$
#1510000
1!
0$
1&
b1001010 )
#1515000
b1110101 "
b1110101 *
b101 0
1$
#1520000
0!
0$
0&
#1525000
1$
#1530000
1!
0$
1&
b1001011 )
#1535000
b1110110 "
b1110110 *
b110 0
1$
#1540000
0!
0$
0&
#1545000
1$
#1550000
1!
0$
1&
b1001100 )
#1555000
b1110111 "
b1110111 *
b111 0
1$
#1560000
0!
0$
0&
#1565000
1$
#1570000
1!
0$
1&
b1001101 )
#1575000
b1111000 "
b1111000 *
b1000 0
1$
#1580000
0!
0$
0&
#1585000
1$
#1590000
1!
0$
1&
b1001110 )
#1595000
b1111001 "
b1111001 *
b1001 0
1$
#1600000
0!
0$
0&
#1605000
1$
#1610000
1!
0$
1&
b1001111 )
#1615000
b1000 /
b10000000 "
b10000000 *
b0 0
1$
#1620000
0!
0$
0&
#1625000
1$
#1630000
1!
0$
1&
b1010000 )
#1635000
b10000001 "
b10000001 *
b1 0
1$
#1640000
0!
0$
0&
#1645000
1$
#1650000
1!
0$
1&
b1010001 )
#1655000
b10000010 "
b10000010 *
b10 0
1$
#1660000
0!
0$
0&
#1665000
1$
#1670000
1!
0$
1&
b1010010 )
#1675000
b10000011 "
b10000011 *
b11 0
1$
#1680000
0!
0$
0&
#1685000
1$
#1690000
1!
0$
1&
b1010011 )
#1695000
b10000100 "
b10000100 *
b100 0
1$
#1700000
0!
0$
0&
#1705000
1$
#1710000
1!
0$
1&
b1010100 )
#1715000
b10000101 "
b10000101 *
b101 0
1$
#1720000
0!
0$
0&
#1725000
1$
#1730000
1!
0$
1&
b1010101 )
#1735000
b10000110 "
b10000110 *
b110 0
1$
#1740000
0!
0$
0&
#1745000
1$
#1750000
1!
0$
1&
b1010110 )
#1755000
b10000111 "
b10000111 *
b111 0
1$
#1760000
0!
0$
0&
#1765000
1$
#1770000
1!
0$
1&
b1010111 )
#1775000
b10001000 "
b10001000 *
b1000 0
1$
#1780000
0!
0$
0&
#1785000
1$
#1790000
1!
0$
1&
b1011000 )
#1795000
b10001001 "
b10001001 *
b1001 0
1$
#1800000
0!
0$
0&
#1805000
1$
#1810000
1!
0$
1&
b1011001 )
#1815000
b1001 /
b10010000 "
b10010000 *
b0 0
1$
#1820000
0!
0$
0&
#1825000
1$
#1830000
1!
0$
1&
b1011010 )
#1835000
b10010001 "
b10010001 *
b1 0
1$
#1840000
0!
0$
0&
#1845000
1$
#1850000
1!
0$
1&
b1011011 )
#1855000
b10010010 "
b10010010 *
b10 0
1$
#1860000
0!
0$
0&
#1865000
1$
#1870000
1!
0$
1&
b1011100 )
#1875000
b10010011 "
b10010011 *
b11 0
1$
#1880000
0!
0$
0&
#1885000
1$
#1890000
1!
0$
1&
b1011101 )
#1895000
b10010100 "
b10010100 *
b100 0
1$
#1900000
0!
0$
0&
#1905000
1$
#1910000
1!
0$
1&
b1011110 )
#1915000
b10010101 "
b10010101 *
b101 0
1$
#1920000
0!
0$
0&
#1925000
1$
#1930000
1!
0$
1&
b1011111 )
#1935000
b10010110 "
b10010110 *
b110 0
1$
#1940000
0!
0$
0&
#1945000
1$
#1950000
1!
0$
1&
b1100000 )
#1955000
b10010111 "
b10010111 *
b111 0
1$
#1960000
0!
0$
0&
#1965000
1$
#1970000
1!
0$
1&
b1100001 )
#1975000
b10011000 "
b10011000 *
b1000 0
1$
#1980000
0!
0$
0&
#1985000
1$
#1990000
1!
0$
1&
b1100010 )
#1995000
b10011001 "
b10011001 *
b1001 0
1$
#2000000
0!
0$
0&
#2005000
1$
#2010000
1!
0$
1&
b1100011 )
#2015000
1$
#2020000
0!
0$
0&
#2025000
1$
#2030000
0$
b1100100 )
#2035000
1$
#2040000
0$
1'
#2045000
b0 /
b0 "
b0 *
b0 0
b0 .
1$
#2050000
0$
0'
#2055000
1$
#2060000
0$
1&
#2065000
b1 "
b1 *
b1 0
b1 .
1$
#2070000
0$
0&
#2075000
1$
#2080000
0$
1&
b1100101 )
#2085000
1!
b10 "
b10 *
b10 0
b10 .
1$
#2090000
0!
0$
0&
#2095000
1$
#2100000
0$
1%
b1100110 )
#2105000
b0 .
1$
#2110000
0$
0%
#2115000
1$
#2120000
0$
1&
#2125000
b11 "
b11 *
b11 0
b1 .
1$
#2130000
0$
0&
#2135000
1$
#2140000
0$
1&
b1100111 )
#2145000
1!
b100 "
b100 *
b100 0
b10 .
1$
#2150000
0!
0$
0&
#2155000
1$
#2160000
1!
0$
1&
b1101000 )
#2165000
b101 "
b101 *
b101 0
b11 .
1$
#2170000
0!
0$
0&
#2175000
1$
#2180000
1!
0$
1&
b1101001 )
#2185000
b110 "
b110 *
b110 0
1$
#2190000
0!
0$
0&
#2195000
1$
#2200000
0$
1%
b1101010 )
#2205000
b0 .
1$
#2210000
0$
0%
#2215000
1$
#2220000
0$
#2225000
1$
#2230000
0$
1&
1'
#2235000
b0 "
b0 *
b0 0
1$
#2240000
0$
0&
0'
#2245000
1$
#2250000
0$
#2255000
1$
#2260000
0$
1&
1(
#2265000
1$
#2270000
0$
0&
0(
